README.md
setup.py
huamulantool/__init__.py
huamulantool/dgrapi.py
huamulantool/jdApi.py
huamulantool.egg-info/PKG-INFO
huamulantool.egg-info/SOURCES.txt
huamulantool.egg-info/dependency_links.txt
huamulantool.egg-info/top_level.txt