Metadata-Version: 1.0
Name: huamulantool
Version: 0.1.11
Summary: jdapi tool
Home-page: https://github.com/15906617886/huamulantool
Author: huamulan
Author-email: 540834498@qq.com
License: MIT Licence
Platform: any
